Metadata-Version: 2.1
Name: super-paczka
Version: 0.0.1
Summary: some desc
Home-page: UNKNOWN
Author: Maciej
License: UNKNOWN
Platform: UNKNOWN
